extractcode_libarchive/__init__.py
extractcode_libarchive/lib/libarchive.dylib
extractcode_libarchive/lib/libb2.1.dylib
extractcode_libarchive/lib/liblz4.1.dylib
extractcode_libarchive/lib/liblzma.5.dylib
extractcode_libarchive/lib/libzstd.1.dylib
extractcode_libarchive/licenses/libarchive/COPYING
extractcode_libarchive/licenses/libarchive/INSTALL_RECEIPT.json
extractcode_libarchive/licenses/libarchive/README.md
extractcode_libarchive/licenses/libb2/COPYING
extractcode_libarchive/licenses/libb2/INSTALL_RECEIPT.json
extractcode_libarchive/licenses/lz4/INSTALL_RECEIPT.json
extractcode_libarchive/licenses/lz4/LICENSE
extractcode_libarchive/licenses/lz4/README.md
extractcode_libarchive/licenses/lz4/lz4.LICENSE
extractcode_libarchive/licenses/xz/AUTHORS
extractcode_libarchive/licenses/xz/COPYING
extractcode_libarchive/licenses/xz/ChangeLog
extractcode_libarchive/licenses/xz/INSTALL_RECEIPT.json
extractcode_libarchive/licenses/xz/README
extractcode_libarchive/licenses/xz/THANKS
extractcode_libarchive/licenses/zstd/CHANGELOG
extractcode_libarchive/licenses/zstd/COPYING
extractcode_libarchive/licenses/zstd/INSTALL_RECEIPT.json
extractcode_libarchive/licenses/zstd/LICENSE
extractcode_libarchive/licenses/zstd/README.md
extractcode_libarchive-3.5.1.210531.dist-info/LICENSE.txt
extractcode_libarchive-3.5.1.210531.dist-info/METADATA
extractcode_libarchive-3.5.1.210531.dist-info/README.rst
extractcode_libarchive-3.5.1.210531.dist-info/WHEEL
extractcode_libarchive-3.5.1.210531.dist-info/apache-2.0.LICENSE
extractcode_libarchive-3.5.1.210531.dist-info/entry_points.txt
extractcode_libarchive-3.5.1.210531.dist-info/top_level.txt
extractcode_libarchive-3.5.1.210531.dist-info/RECORD
